LICENSE
MANIFEST.in
README.rst
requirements.txt
setup.cfg
setup.py
docs/.gitignore
docs/Makefile
docs/api.rst
docs/check_sphinx.py
docs/conf.py
docs/index.rst
docs/make.bat
docs/ref/accounts.rst
docs/ref/appliance_config.rst
docs/ref/exceptions.rst
docs/ref/groups.rst
docs/ref/index.rst
docs/ref/pages.rst
docs/ref/signals.rst
docs/ref/uploads.rst
docs/ref/users.rst
docs/ref/webhooks.rst
docs/ref/workspaces.rst
python_socialtext.egg-info/PKG-INFO
python_socialtext.egg-info/SOURCES.txt
python_socialtext.egg-info/dependency_links.txt
python_socialtext.egg-info/entry_points.txt
python_socialtext.egg-info/requires.txt
python_socialtext.egg-info/top_level.txt
socialtext/__init__.py
socialtext/client.py
socialtext/exceptions.py
socialtext/shell.py
socialtext/urls.py
socialtext/resources/__init__.py
socialtext/resources/appliance_config.py
socialtext/resources/base.py
socialtext/resources/uploads.py
socialtext/resources/users.py
socialtext/resources/webhooks.py
socialtext/resources/accounts/__init__.py
socialtext/resources/accounts/base.py
socialtext/resources/accounts/members.py
socialtext/resources/groups/__init__.py
socialtext/resources/groups/base.py
socialtext/resources/groups/trash.py
socialtext/resources/pages/__init__.py
socialtext/resources/pages/backlinks.py
socialtext/resources/pages/base.py
socialtext/resources/pages/comments.py
socialtext/resources/pages/frontlinks.py
socialtext/resources/pages/revisions.py
socialtext/resources/pages/tags.py
socialtext/resources/signals/__init__.py
socialtext/resources/signals/base.py
socialtext/resources/signals/likes.py
socialtext/resources/workspaces/__init__.py
socialtext/resources/workspaces/base.py
socialtext/resources/workspaces/tags.py
tests/__init__.py
tests/__init__.pyc
tests/fakeserver.py
tests/fakeserver.pyc
tests/test_appliance_config.py
tests/test_appliance_config.pyc
tests/test_base.py
tests/test_base.pyc
tests/test_client.py
tests/test_client.pyc
tests/test_exceptions.py
tests/test_exceptions.pyc
tests/test_urls.py
tests/test_urls.pyc
tests/utils.py
tests/utils.pyc
tests/test_accounts/__init__.py
tests/test_accounts/__init__.pyc
tests/test_accounts/test_manager.py
tests/test_accounts/test_manager.pyc
tests/test_accounts/test_members.py
