Metadata-Version: 1.0
Name: python-socialtext
Version: 0.2.3
Summary: Python binding for the Socialtext REST API
Home-page: UNKNOWN
Author: Justin Murphy, The Hanover Insurance Group
Author-email: ju1murphy@hanover.com
License: UNKNOWN
Platform: UNKNOWN
Classifier: Intended Audience :: Developers
Classifier: Intended Audience :: Information Technology
Classifier: License :: OSI Approved :: Apache Software License
Classifier: Operating System :: OS Independent
Classifier: Programming Language :: Python
Classifier: Programming Language :: Python :: 2
Classifier: Programming Language :: Python :: 2.5
Classifier: Programming Language :: Python :: 2.6
Classifier: Programming Language :: Python :: 2.7
